{"32000":["DZ","32000","Bougtob Hai Nasr","El-Bayadh","32","","","","","33.4156","0.8799","1"],"32001":["DZ","32001","Bougtob Hai Nasr","El-Bayadh","32","","","","","33.9532","0.2052","3"],"32002":["DZ","32002","Hassi Bendella","El-Bayadh","32","","","","","33.0028","1.244","3"],"32003":["DZ","32003","El Abiodh Sidi Cheikh","El-Bayadh","32","","","","","32.893","0.5484","4"],"32004":["DZ","32004","El Bayadh Toumi Mohamed","El-Bayadh","32","","","","","33.4156","0.8799","1"],"32005":["DZ","32005","Arbaouat","El-Bayadh","32","","","","","33.0881","0.5803","4"],"32006":["DZ","32006","Sidi Ahmed Ben Aissa","El-Bayadh","32","","","","","33.7158","1.5059","3"],"32007":["DZ","32007","El Abiodh Sidi Cheikh Belmabrouk","El-Bayadh","32","","","","","33.4156","0.8799","1"],"32008":["DZ","32008","El Bayadh Ait Amiri","El-Bayadh","32","","","","","33.4156","0.8799","1"],"32009":["DZ","32009","El Bayadh Hamidi Boulenouar","El-Bayadh","32","","","","","33.4156","0.8799","1"],"32010":["DZ","32010","El Bayadh Hasnaoui  Said","El-Bayadh","32","","","","","33.1714","0.5044","1"],"32011":["DZ","32011","El Kheither","El-Bayadh","32","","","","","33.1714","0.5044","1"],"32012":["DZ","32012","Hossein Ibn Ali","El-Bayadh","32","","","","","33.1714","0.5044","1"],"32013":["DZ","32013","Megrane","El-Bayadh","32","","","","","33.1714","0.5044","1"],"32014":["DZ","32014","Boussemghoun","El-Bayadh","32","","","","","32.8643","0.0201","4"],"32015":["DZ","32015","Chellala Dahrania","El-Bayadh","32","","","","","33.0339","0.0561","4"],"32016":["DZ","32016","El Bayadh Kadichou Mohamed","El-Bayadh","32","","","","","33.1714","0.5044","1"],"32017":["DZ","32017","Lekhchim","El-Bayadh","32","","","","","33.3772","1.2027","3"],"32018":["DZ","32018","Hemeimat","El-Bayadh","32","","","","","33.1714","0.5044","1"],"32019":["DZ","32019","Rouissa","El-Bayadh","32","","","","","33.4102","0.7385","3"],"32020":["DZ","32020","Arba Fougani","El-Bayadh","32","","","","","33.0132","0.1084","1"],"32021":["DZ","32021","Bordj El May","El-Bayadh","32","","","","","33.0132","0.1084","1"],"32022":["DZ","32022","Sefira","El-Bayadh","32","","","","","33.0132","0.1084","1"],"32023":["DZ","32023","Maider","El-Bayadh","32","","","","","33.0132","0.1084","3"],"32024":["DZ","32024","Deghima","El-Bayadh","32","","","","","33.0132","0.1084","1"],"32025":["DZ","32025","El Bnoud","El-Bayadh","32","","","","","33.0132","0.1084","1"],"32026":["DZ","32026","El Mehara","El-Bayadh","32","","","","","33.0132","0.1084","1"],"32027":["DZ","32027","El Meghsel","El-Bayadh","32","","","","","33.0132","0.1084","1"],"32028":["DZ","32028","Mosbah","El-Bayadh","32","","","","","33.0132","0.1084","1"],"32029":["DZ","32029","Ain Djedida","El-Bayadh","32","","","","","33.0132","0.1084","1"],"32030":["DZ","32030","Sidi Khelifa","El-Bayadh","32","","","","","33.7409","1.2372","1"],"32031":["DZ","32031","Sidi Slimane","El-Bayadh","32","","","","","33.8333","1.7298","4"],"32032":["DZ","32032","Dir El Hassiane","El-Bayadh","32","","","","","33.7213","1.6866","3"],"32033":["DZ","32033","Oudei El Hgel","El-Bayadh","32","","","","","33.7569","1.2237","3"],"32034":["DZ","32034","Tousmouline","El-Bayadh","32","","","","","33.6519","0.3086","4"]}