{"35000":["DZ","35000","Youbi (Douar)","Boumerdes","35","","","","","36.7724","3.7041","1"],"35001":["DZ","35001","Grenier (Ferme)","Boumerdes","35","","","","","36.7705","3.7174","3"],"35002":["DZ","35002","Bordj Menaiel Amirouche","Boumerdes","35","","","","","36.7724","3.7041","1"],"35003":["DZ","35003","Cite Sonelgaz","Boumerdes","35","","","","","36.7274","3.4099","3"],"35004":["DZ","35004","Ioualaichen","Boumerdes","35","","","","","36.9023","3.8947","3"],"35005":["DZ","35005","Capcs","Boumerdes","35","","","","","36.7254","3.5567","3"],"35006":["DZ","35006","Ouled Amar","Boumerdes","35","","","","","36.6677","3.5912","3"],"35007":["DZ","35007","Boumerdes Franz Fanon","Boumerdes","35","","","","","36.7724","3.7041","1"],"35008":["DZ","35008","Azouza (Douar)","Boumerdes","35","","","","","36.6371","3.6947","3"],"35009":["DZ","35009","Ecole De Tourfa","Boumerdes","35","","","","","36.7186","3.6692","3"],"35010":["DZ","35010","Zerzour Rabah (Domaine)","Boumerdes","35","","","","","36.3674","2.8762","3"],"35011":["DZ","35011","Djelloula (Douar)","Boumerdes","35","","","","","36.6419","3.4261","3"],"35012":["DZ","35012","Guellal","Boumerdes","35","","","","","36.4679","2.8615","3"],"35013":["DZ","35013","Grima (Ferme)","Boumerdes","35","","","","","36.684","3.6748","3"],"35014":["DZ","35014","Ain Abdellah (Douar)","Boumerdes","35","","","","","36.6215","3.4191","1"],"35015":["DZ","35015","Mouassia (Douar)","Boumerdes","35","","","","","36.6215","3.4191","1"],"35016":["DZ","35016","Djaouma (Douar)","Boumerdes","35","","","","","36.6215","3.4191","1"],"35017":["DZ","35017","Boumeziane (Domaine)","Boumerdes","35","","","","","36.6215","3.4191","1"],"35018":["DZ","35018","Village Agricole","Boumerdes","35","","","","","36.7253","3.7286","3"],"35019":["DZ","35019","Souamine","Boumerdes","35","","","","","36.8558","3.8567","3"],"35020":["DZ","35020","Bouhara","Boumerdes","35","","","","","36.6906","3.5891","3"],"35021":["DZ","35021","Tarafi","Boumerdes","35","","","","","36.7305","3.4948","3"],"35022":["DZ","35022","Oued El Ahssar","Boumerdes","35","","","","","36.7908","3.9311","3"],"35023":["DZ","35023","Boudouaou Benterquia","Boumerdes","35","","","","","36.7806","3.7435","1"],"35024":["DZ","35024","Ouled Ghanim","Boumerdes","35","","","","","36.8781","3.7231","3"],"35025":["DZ","35025","Bouagada","Boumerdes","35","","","","","36.8036","3.6613","3"],"35026":["DZ","35026","Taoural","Boumerdes","35","","","","","36.8021","3.6755","3"],"35027":["DZ","35027","Ouanougha","Boumerdes","35","","","","","36.7273","3.7415","3"],"35028":["DZ","35028","Mechairi Lounes","Boumerdes","35","","","","","36.7233","3.6181","3"],"35029":["DZ","35029","El Kodiat","Boumerdes","35","","","","","36.836","3.8478","3"],"35030":["DZ","35030","Abada","Boumerdes","35","","","","","36.7719","3.4055","1"],"35031":["DZ","35031","Ammal Agglomeration","Boumerdes","35","","","","","36.7719","3.4055","1"],"35032":["DZ","35032","Azrou","Boumerdes","35","","","","","36.7719","3.4055","1"],"35033":["DZ","35033","Benchoud","Boumerdes","35","","","","","36.7719","3.4055","1"],"35034":["DZ","35034","Benmerzouga","Boumerdes","35","","","","","36.7719","3.4055","1"],"35035":["DZ","35035","Bouaidel","Boumerdes","35","","","","","36.7719","3.4055","1"],"35036":["DZ","35036","Tala Mali (Douar)","Boumerdes","35","","","","","36.7719","3.4055","1"],"35037":["DZ","35037","Boudouaou El Bahri","Boumerdes","35","","","","","36.7719","3.4055","4"],"35038":["DZ","35038","Bouzegza Kedara","Boumerdes","35","","","","","36.7719","3.4055","1"],"35039":["DZ","35039","Haouchine (Douar)","Boumerdes","35","","","","","36.7719","3.4055","1"],"35040":["DZ","35040","Chlef Boumraou","Boumerdes","35","","","","","36.7055","3.5237","1"],"35041":["DZ","35041","Oued Hellal","Boumerdes","35","","","","","36.7055","3.5237","1"],"35042":["DZ","35042","Ghazibaouene","Boumerdes","35","","","","","36.6365","3.5331","3"],"35043":["DZ","35043","Hadj Ahmed","Boumerdes","35","","","","","36.7055","3.5237","1"],"35044":["DZ","35044","Haouch Ben Ouali","Boumerdes","35","","","","","36.7055","3.5237","1"],"35045":["DZ","35045","Haouch El Mokhfi","Boumerdes","35","","","","","36.7055","3.5237","1"],"35046":["DZ","35046","Thibaut","Boumerdes","35","","","","","36.7744","3.5143","3"],"35047":["DZ","35047","Kehf El Gharbi","Boumerdes","35","","","","","36.7055","3.5237","1"],"35048":["DZ","35048","Bouzegza Pepiniere","Boumerdes","35","","","","","36.7055","3.5237","1"],"35049":["DZ","35049","Khemis El Khechna 17 Juin","Boumerdes","35","","","","","36.7055","3.5237","1"],"35050":["DZ","35050","Ouled Aissa","Boumerdes","35","","","","","36.6823","3.5918","1"],"35051":["DZ","35051","Ouled Ali","Boumerdes","35","","","","","36.8117","3.7358","4"],"35052":["DZ","35052","Ouled Hadadj","Boumerdes","35","","","","","36.6823","3.5918","1"],"35053":["DZ","35053","Cherraba","Boumerdes","35","","","","","36.0166","2.4152","3"],"35054":["DZ","35054","Ouriacha","Boumerdes","35","","","","","36.6818","3.8477","4"],"35055":["DZ","35055","Sebaou El Kedim","Boumerdes","35","","","","","36.7798","3.873","4"],"35056":["DZ","35056","Sidi El Medjni","Boumerdes","35","","","","","36.6823","3.5918","1"],"35057":["DZ","35057","Takdempt","Boumerdes","35","","","","","36.9048","3.8444","4"],"35058":["DZ","35058","Kais Ali (Ferme)","Boumerdes","35","","","","","36.8993","3.8348","3"],"35059":["DZ","35059","Talaoubrid","Boumerdes","35","","","","","36.6823","3.5918","1"],"35060":["DZ","35060","Zaatra","Boumerdes","35","","","","","36.7675","3.6069","4"],"35061":["DZ","35061","Zemmouri El Bahri","Boumerdes","35","","","","","36.8028","3.565","4"],"35062":["DZ","35062","Bouomerdes Le Rocher","Boumerdes","35","","","","","36.7851","3.586","1"]}